resume_screening_mcp/__init__.py
resume_screening_mcp/__main__.py
resume_screening_mcp/cli.py
resume_screening_mcp/core.py
resume_screening_mcp/server.py
resume_screening_mcp-0.1.6.dist-info/METADATA
resume_screening_mcp-0.1.6.dist-info/WHEEL
resume_screening_mcp-0.1.6.dist-info/entry_points.txt
resume_screening_mcp-0.1.6.dist-info/top_level.txt
resume_screening_mcp-0.1.6.dist-info/RECORD
