Metadata-Version: 2.4
Name: resume_screening_mcp
Version: 0.1.6
Summary: Resume screening service using LLM
Author-email: User <user@example.com>
Classifier: Programming Language :: Python :: 3
Classifier: License :: OSI Approved :: MIT License
Classifier: Operating System :: OS Independent
Requires-Python: >=3.10
Requires-Dist: fastmcp
Requires-Dist: openai>=1.0.0
Requires-Dist: PyPDF2
Requires-Dist: python-docx
Requires-Dist: pandas
Requires-Dist: pdfplumber
Requires-Dist: python-dotenv
Requires-Dist: openpyxl
Provides-Extra: dev
Requires-Dist: pytest; extra == "dev"
Requires-Dist: black; extra == "dev"
Requires-Dist: isort; extra == "dev"
